question_cls/__init__.py
question_cls/ques_cls.py
ques-0.0.1.dist-info/METADATA
ques-0.0.1.dist-info/WHEEL
ques-0.0.1.dist-info/top_level.txt
ques-0.0.1.dist-info/RECORD
