Metadata-Version: 2.1
Name: ques
Version: 0.0.1
Requires-Dist: requests
Requires-Dist: importlib-metadata ; python_version < "3.10"
